Simple_Process_REPL/SPR-defaults.yaml
Simple_Process_REPL/__init__.py
Simple_Process_REPL/__main__.py
Simple_Process_REPL/appstate.py
Simple_Process_REPL/appstate.spr
Simple_Process_REPL/bar_qr.py
Simple_Process_REPL/bar_qr.spr
Simple_Process_REPL/cli.py
Simple_Process_REPL/cli.spr
Simple_Process_REPL/core.py
Simple_Process_REPL/core.spr
Simple_Process_REPL/device.py
Simple_Process_REPL/device.spr
Simple_Process_REPL/dialog.py
Simple_Process_REPL/dialog.spr
Simple_Process_REPL/dialog.yaml
Simple_Process_REPL/logs.py
Simple_Process_REPL/main.py
Simple_Process_REPL/markdown.py
Simple_Process_REPL/markdown.yaml
Simple_Process_REPL/mkext.py
Simple_Process_REPL/network.py
Simple_Process_REPL/network.yaml
Simple_Process_REPL/options.py
Simple_Process_REPL/particle.py
Simple_Process_REPL/particle_main.py
Simple_Process_REPL/particle_main.spr
Simple_Process_REPL/python.txt
Simple_Process_REPL/readme.txt
Simple_Process_REPL/repl.py
Simple_Process_REPL/repl.spr
Simple_Process_REPL/setup.txt
Simple_Process_REPL/spr.txt
Simple_Process_REPL/subcmd.py
Simple_Process_REPL/utils.py
Simple_Process_REPL/webview.py
Simple_Process_REPL/webview.yaml
Simple_Process_REPL/yaml.txt
Simple_Process_REPL-2.0.3.dist-info/METADATA
Simple_Process_REPL-2.0.3.dist-info/WHEEL
Simple_Process_REPL-2.0.3.dist-info/entry_points.txt
Simple_Process_REPL-2.0.3.dist-info/top_level.txt
Simple_Process_REPL-2.0.3.dist-info/RECORD
