Metadata-Version: 2.1
Name: Simple-Process-REPL
Version: 2.0.3
Summary: An extensible application framework with REPL for creating processes with side effects.
Home-page: https://github.com/EricGebhart/Simple_Process_REPL
Author: Eric Gebhart
Author-email: e.a.gebhart@gmail.com
License: MIT
Platform: UNKNOWN
Requires-Dist: pyserial
Requires-Dist: pythondialog
Requires-Dist: pyYAML
Requires-Dist: regex
Requires-Dist: python-barcode
Requires-Dist: qrcode
Requires-Dist: Pillow
Requires-Dist: opencv-python
Requires-Dist: numpy
Requires-Dist: Image
Requires-Dist: Pyzbar
Requires-Dist: markdown
